drivesecrets/__init__.py
drivesecrets/main.py
drivesecrets-1.0.0.dist-info/LICENSE
drivesecrets-1.0.0.dist-info/WHEEL
drivesecrets-1.0.0.dist-info/METADATA
drivesecrets-1.0.0.dist-info/RECORD
